sphinxcontrib_del_marker-0.1.2.dist-info/METADATA
sphinxcontrib_del_marker-0.1.2.dist-info/WHEEL
sphinxcontrib_del_marker-0.1.2.dist-info/licenses/LICENSE
sphinxcontrib_del_marker/__init__.py
sphinxcontrib_del_marker/del_marker.py
sphinxcontrib_del_marker-0.1.2.dist-info/RECORD
