Metadata-Version: 2.1
Name: sphinxcontrib-del-marker
Version: 0.1.2
Summary: A sphinx plugin that enables embedding of HTML5 del
Author-Email: jennier0107 <mt3085570450@outlook.com>
License: MIT
Requires-Python: >=3.11
Requires-Dist: Sphinx>=7.3.7
Requires-Dist: sphinxcontrib-serializinghtml>=1.1.10
